bandcamper/__init__.py
bandcamper/__main__.py
bandcamper/__version__.py
bandcamper/bandcamper.py
bandcamper/metadata/__init__.py
bandcamper/metadata/aiff.py
bandcamper/metadata/flac.py
bandcamper/metadata/mp3.py
bandcamper/metadata/mp4.py
bandcamper/metadata/track_metadata.py
bandcamper/metadata/utils.py
bandcamper/metadata/vorbis.py
bandcamper/metadata/wave.py
bandcamper/requests/__init__.py
bandcamper/requests/requester.py
bandcamper/requests/utils.py
bandcamper/screamo.py
bandcamper/utils.py
bandcamper-0.0.2.dist-info/LICENSE
bandcamper-0.0.2.dist-info/METADATA
bandcamper-0.0.2.dist-info/WHEEL
bandcamper-0.0.2.dist-info/entry_points.txt
bandcamper-0.0.2.dist-info/RECORD
