Metadata-Version: 2.1
Name: bandcamper
Version: 0.0.2
Summary: Bandcamp downloader.
Home-page: https://github.com/yyyyyyyan/bandcamper
License: MIT
Keywords: bandcamp,downloader,music
Author: yyyyyyyan
Author-email: contact@yyyyyyyan.tech
Requires-Python: >=3.7,<4.0
Classifier: Development Status :: 3 - Alpha
Classifier: Environment :: Console
Classifier: Intended Audience :: End Users/Desktop
Classifier: License :: OSI Approved :: MIT License
Classifier: Natural Language :: English
Classifier: Operating System :: OS Independent
Classifier: Programming Language :: Python :: 3
Classifier: Programming Language :: Python :: 3.7
Classifier: Programming Language :: Python :: 3.8
Classifier: Programming Language :: Python :: 3.9
Classifier: Programming Language :: Python :: 3.10
Classifier: Programming Language :: Python :: 3.11
Classifier: Programming Language :: Python :: 3 :: Only
Classifier: Topic :: Communications :: File Sharing
Classifier: Topic :: Internet
Classifier: Topic :: Multimedia :: Sound/Audio
Classifier: Topic :: Utilities
Requires-Dist: beautifulsoup4 (>=4.10.0)
Requires-Dist: click (>=8.0.1)
Requires-Dist: click-option-group (>=0.5.3)
Requires-Dist: lxml (>=4.6.3)
Requires-Dist: mutagen (>=1.45.1)
Requires-Dist: onesecmail (>=0.0.1)
Requires-Dist: pathvalidate (>=3.1.0)
Requires-Dist: requests[socks] (>=2.26.0)
Project-URL: Repository, https://github.com/yyyyyyyan/bandcamper
